aliyunsdkice/__init__.py
aliyunsdkice/endpoint.py
aliyunsdkice/request/__init__.py
aliyunsdkice/request/v20201109/AddCategoryRequest.py
aliyunsdkice/request/v20201109/AddEditingProjectMaterialsRequest.py
aliyunsdkice/request/v20201109/AddFavoritePublicMediaRequest.py
aliyunsdkice/request/v20201109/AddMediaMarksRequest.py
aliyunsdkice/request/v20201109/AddTemplateRequest.py
aliyunsdkice/request/v20201109/BatchGetMediaInfosRequest.py
aliyunsdkice/request/v20201109/CancelDNAJobRequest.py
aliyunsdkice/request/v20201109/CancelFavoritePublicMediaRequest.py
aliyunsdkice/request/v20201109/CreateAuditRequest.py
aliyunsdkice/request/v20201109/CreateCustomTemplateRequest.py
aliyunsdkice/request/v20201109/CreateDNADBRequest.py
aliyunsdkice/request/v20201109/CreateEditingProjectRequest.py
aliyunsdkice/request/v20201109/CreateLiveRecordTemplateRequest.py
aliyunsdkice/request/v20201109/CreateLiveSnapshotTemplateRequest.py
aliyunsdkice/request/v20201109/CreateLiveTranscodeTemplateRequest.py
aliyunsdkice/request/v20201109/CreatePipelineRequest.py
aliyunsdkice/request/v20201109/CreateUploadMediaRequest.py
aliyunsdkice/request/v20201109/CreateUploadStreamRequest.py
aliyunsdkice/request/v20201109/DeleteCategoryRequest.py
aliyunsdkice/request/v20201109/DeleteCustomTemplateRequest.py
aliyunsdkice/request/v20201109/DeleteDNADBRequest.py
aliyunsdkice/request/v20201109/DeleteDNAFilesRequest.py
aliyunsdkice/request/v20201109/DeleteEditingProjectMaterialsRequest.py
aliyunsdkice/request/v20201109/DeleteEditingProjectsRequest.py
aliyunsdkice/request/v20201109/DeleteLiveRecordFilesRequest.py
aliyunsdkice/request/v20201109/DeleteLiveRecordTemplateRequest.py
aliyunsdkice/request/v20201109/DeleteLiveSnapshotFilesRequest.py
aliyunsdkice/request/v20201109/DeleteLiveSnapshotTemplateRequest.py
aliyunsdkice/request/v20201109/DeleteLiveTranscodeJobRequest.py
aliyunsdkice/request/v20201109/DeleteLiveTranscodeTemplateRequest.py
aliyunsdkice/request/v20201109/DeleteMediaInfosRequest.py
aliyun_python_sdk_ice-1.0.2.dist-info/LICENSE
aliyun_python_sdk_ice-1.0.2.dist-info/METADATA
aliyun_python_sdk_ice-1.0.2.dist-info/WHEEL
aliyun_python_sdk_ice-1.0.2.dist-info/top_level.txt
aliyun_python_sdk_ice-1.0.2.dist-info/RECORD
